pankoclient/__init__.py
pankoclient/client.py
pankoclient/exceptions.py
pankoclient/osc.py
pankoclient/shell.py
pankoclient/utils.py
pankoclient/common/__init__.py
pankoclient/common/base.py
pankoclient/common/i18n.py
pankoclient/tests/__init__.py
pankoclient/tests/functional/__init__.py
pankoclient/tests/functional/base.py
pankoclient/tests/unit/__init__.py
pankoclient/tests/unit/base.py
pankoclient/tests/unit/fakes.py
pankoclient/tests/unit/test_osc_plugin.py
pankoclient/tests/unit/common/__init__.py
pankoclient/tests/unit/common/test_base.py
pankoclient/tests/unit/v2/__init__.py
pankoclient/tests/unit/v2/test_events.py
pankoclient/v2/__init__.py
pankoclient/v2/capabilities.py
pankoclient/v2/capabilities_cli.py
pankoclient/v2/client.py
pankoclient/v2/events.py
pankoclient/v2/events_cli.py
pankoclient-1.2.0.dist-info/AUTHORS
pankoclient-1.2.0.dist-info/LICENSE
pankoclient-1.2.0.dist-info/METADATA
pankoclient-1.2.0.dist-info/WHEEL
pankoclient-1.2.0.dist-info/entry_points.txt
pankoclient-1.2.0.dist-info/pbr.json
pankoclient-1.2.0.dist-info/top_level.txt
pankoclient-1.2.0.dist-info/RECORD
