Metadata-Version: 2.1
Name: pankoclient
Version: 1.2.0
Summary: Python client library for OpenStack Panko project.
Home-page: https://docs.openstack.org/python-pankoclient/latest/
Author: OpenStack
Author-email: openstack-discuss@lists.openstack.org
License: Apache License, Version 2.0
Platform: UNKNOWN
Classifier: Development Status :: 5 - Production/Stable
Classifier: Environment :: Console
Classifier: Environment :: OpenStack
Classifier: Intended Audience :: Information Technology
Classifier: Intended Audience :: System Administrators
Classifier: License :: OSI Approved :: Apache Software License
Classifier: Operating System :: POSIX :: Linux
Classifier: Programming Language :: Python
Classifier: Programming Language :: Python :: Implementation :: CPython
Classifier: Programming Language :: Python :: 3 :: Only
Classifier: Programming Language :: Python :: 3
Classifier: Programming Language :: Python :: 3.6
Classifier: Programming Language :: Python :: 3.7
Classifier: Programming Language :: Python :: 3.8
Requires-Python: >=3.6
Requires-Dist: keystoneauth1 (>=3.4.0)
Requires-Dist: osc-lib (>=1.8.0)
Requires-Dist: oslo.i18n (>=2.1.0)
Requires-Dist: oslo.serialization (>=1.10.0)
Requires-Dist: oslo.utils (>=3.18.0)
Requires-Dist: osprofiler (>=1.4.0)
Requires-Dist: pbr (>=1.8)
Requires-Dist: requests (>=2.14.2)
Requires-Dist: six (>=1.9.0)
Provides-Extra: test
Requires-Dist: coverage (>=4.0) ; extra == 'test'
Requires-Dist: hacking (<3.1.0,>=3.0) ; extra == 'test'
Requires-Dist: oslotest (>=1.10.0) ; extra == 'test'
Requires-Dist: python-openstackclient (>=3.3.0) ; extra == 'test'
Requires-Dist: reno (>=1.8.0) ; extra == 'test'
Requires-Dist: requests-mock (>=1.1) ; extra == 'test'
Requires-Dist: testrepository (>=0.0.18) ; extra == 'test'
Requires-Dist: testscenarios (>=0.4) ; extra == 'test'
